<!DOCTYPE ui:UiBinder SYSTEM "http://dl.google.com/gwt/DTD/xhtml.ent">
<ui:UiBinder xmlns:ui="urn:ui:com.google.gwt.uibinder"
	xmlns:g="urn:import:com.google.gwt.user.client.ui"
	xmlns:my="urn:import:edu.arizona.biosemantics.etcsite.client.common">
	<ui:style>
		.helpIcon {
		    /*background-image: url('images/Help.gif');*/
		    position: absolute; 
		    background-size: contain; 
		    top: 5px;
		    right: 10px;
		    width: 120px;
		    height: 20px;
		}
		.helpText {
		    position: absolute;
		    top: 8px;
		    right: 15px;
		}
		.loginButtonDiv {
		    /*background-image: url('images/Button.gif');
		    background-size: 100% 100%;
		    width: 70px;
		    height: 20px; */
		    position: absolute;
		    top: 2px;
		    right: 150px;
		}
		.loginButton {
			height: 25px;
			width: 60px;
			padding-top: 2px;
		}
		.passwordField {
		    width: 130px;
		    position: absolute;
		    top: 2px;
		    right: 240px;
		}
		.passwordTextBox {
			height: 13px;
			width: 130px;	
		}
		.userField {
		    width: 130px;
		    position: absolute;
		    top: 2px;
		    right: 400px;
		    height: 25px;
		}
		.userTextBox {
			height: 13px;
			width: 130px;
		}
		.clickable {
			cursor: pointer;
		}
		.loginText {
		    position: absolute;
		    top: 8px;
		    right: 350px;
		}
		.orText {
		    position: absolute;
		    top: 8px;
		    right: 310px;
		}
		.registerText {
		    position: absolute;
		    top: 8px;
		    right: 180px;
		}
		
	</ui:style>
	<g:HTMLPanel>
		<div class="{style.helpIcon} {style.clickable}">
			<my:ImageLabel imagePath="images/Help.gif" imageWidth="20px" imageHeight="20px" text="How to start" ui:field="help"></my:ImageLabel>
		</div>
		<div class="{style.loginText} {style.clickable}">
			<g:Label text="Sign in" ui:field="loginLabel"></g:Label>
		</div>
		<div class="{style.orText}">
			or
		</div>
		<div class="{style.registerText} {style.clickable}">
			<g:Label text="Create an account" ui:field="registerLabel"></g:Label>
		</div>
		
	</g:HTMLPanel>
</ui:UiBinder> 
